BinaryTree.py
LinkedList.py
Trie.py
UnionFind.py
__init__.py
dsakit-2.0.1.dist-info/LICENSE
dsakit-2.0.1.dist-info/METADATA
dsakit-2.0.1.dist-info/WHEEL
dsakit-2.0.1.dist-info/top_level.txt
dsakit-2.0.1.dist-info/RECORD
