Metadata-Version: 2.1
Name: dsakit
Version: 2.0.1
Summary: A package aimed at providing various data structures and their functions to solve dsa problems
Author-email: Aayush65 <cdtaayushgupta@gmail.com>
Project-URL: Homepage, https://github.com/Aayush65/DSAKit
Project-URL: Bug Tracker, https://github.com/Aayush65/DSAKit/issues
Classifier: Programming Language :: Python :: 3
Classifier: License :: OSI Approved :: MIT License
Classifier: Operating System :: OS Independent
Requires-Python: >=3.7
License-File: LICENSE
